Metadata-Version: 1.1
Name: jw.ui.base
Version: 0.1
Summary: Base interface for generic user interface
Home-page: https://pypi.python.org/pypi/jw.ui.base
Author: Johnny Wezel
Author-email: dev-jay@wezel.name
License: Apache2
Keywords: gui ui user interface
Platform: UNKNOWN
Classifier: Development Status :: 4 - Beta
Classifier: Environment :: X11 Applications
Classifier: Intended Audience :: Developers
Classifier: License :: OSI Approved :: Apache Software License
Classifier: Natural Language :: English
Classifier: Operating System :: POSIX
Classifier: Operating System :: Unix
Classifier: Programming Language :: Python :: 2
Classifier: Programming Language :: Python :: 2.7
Classifier: Programming Language :: Python :: 3
Classifier: Programming Language :: Python :: 3.4
